{"cameraMode":{"drawMode":0,"name":"Shaded","section":"Shading Mode"},"sceneLighting":true,"audioPlay":false,"sceneViewState":{"m_AlwaysRefresh":false,"showFog":true,"showSkybox":true,"showFlares":true,"showImageEffects":true,"showParticleSystems":true,"showVisualEffectGraphs":true,"m_FxEnabled":true},"in2DMode":false,"pivot":{"x":0.8998297452926636,"y":2.096518039703369,"z":-10.926248550415039},"rotation":{"x":-0.009876145049929619,"y":-0.9893690347671509,"z":0.08061665296554566,"w":-0.12082165479660034},"size":0.004154585767537355,"orthographic":false}